{
"pages":6,
"measures":55,
"time": [{
    "position": 0,
    "elid": 0
  }, {
    "position": 2400,
    "elid": 1
  }, {
    "position": 4800,
    "elid": 2
  }, {
    "position": 7200,
    "elid": 3
  }, {
    "position": 9600,
    "elid": 4
  }, {
    "position": 12000,
    "elid": 5
  }, {
    "position": 14400,
    "elid": 6
  }, {
    "position": 16800,
    "elid": 7
  }, {
    "position": 19200,
    "elid": 0
  }, {
    "position": 21600,
    "elid": 1
  }, {
    "position": 24000,
    "elid": 2
  }, {
    "position": 26400,
    "elid": 3
  }, {
    "position": 28800,
    "elid": 4
  }, {
    "position": 31200,
    "elid": 5
  }, {
    "position": 33600,
    "elid": 6
  }, {
    "position": 36000,
    "elid": 7
  }, {
    "position": 38400,
    "elid": 8
  }, {
    "position": 40800,
    "elid": 9
  }, {
    "position": 43200,
    "elid": 10
  }, {
    "position": 45600,
    "elid": 11
  }, {
    "position": 48000,
    "elid": 12
  }, {
    "position": 50400,
    "elid": 13
  }, {
    "position": 52800,
    "elid": 14
  }, {
    "position": 55200,
    "elid": 15
  }, {
    "position": 57600,
    "elid": 16
  }, {
    "position": 60000,
    "elid": 17
  }, {
    "position": 62400,
    "elid": 18
  }, {
    "position": 64800,
    "elid": 19
  }, {
    "position": 67200,
    "elid": 20
  }, {
    "position": 69600,
    "elid": 21
  }, {
    "position": 72000,
    "elid": 22
  }, {
    "position": 74400,
    "elid": 23
  }, {
    "position": 76800,
    "elid": 24
  }, {
    "position": 79200,
    "elid": 25
  }, {
    "position": 81600,
    "elid": 26
  }, {
    "position": 84000,
    "elid": 27
  }, {
    "position": 86400,
    "elid": 28
  }, {
    "position": 88800,
    "elid": 29
  }, {
    "position": 91200,
    "elid": 30
  }, {
    "position": 93600,
    "elid": 31
  }, {
    "position": 96000,
    "elid": 32
  }, {
    "position": 98400,
    "elid": 33
  }, {
    "position": 100800,
    "elid": 34
  }, {
    "position": 103200,
    "elid": 35
  }, {
    "position": 105600,
    "elid": 36
  }, {
    "position": 108000,
    "elid": 37
  }, {
    "position": 110400,
    "elid": 38
  }, {
    "position": 112800,
    "elid": 39
  }, {
    "position": 115200,
    "elid": 40
  }, {
    "position": 117600,
    "elid": 41
  }, {
    "position": 120000,
    "elid": 42
  }, {
    "position": 122400,
    "elid": 43
  }, {
    "position": 124800,
    "elid": 44
  }, {
    "position": 127200,
    "elid": 45
  }, {
    "position": 129600,
    "elid": 46
  }, {
    "position": 132000,
    "elid": 47
  }, {
    "position": 134400,
    "elid": 48
  }, {
    "position": 136800,
    "elid": 49
  }, {
    "position": 139200,
    "elid": 50
  }, {
    "position": 141600,
    "elid": 51
  }, {
    "position": 144000,
    "elid": 52
  }, {
    "position": 146400,
    "elid": 53
  }, {
    "position": 148800,
    "elid": 54
  }],
"space": [{
    "id": 0,
    "page": 1,
    "sy": 6180.17,
    "y": 7611.02,
    "sx": 16163.3,
    "x": 4039.37
  }, {
    "id": 1,
    "page": 1,
    "sy": 6180.17,
    "y": 7611.02,
    "sx": 12972.9,
    "x": 20202.7
  }, {
    "id": 2,
    "page": 1,
    "sy": 5357.48,
    "y": 18255.8,
    "sx": 16377.4,
    "x": 2551.18
  }, {
    "id": 3,
    "page": 1,
    "sy": 5357.48,
    "y": 18255.8,
    "sx": 14247,
    "x": 18928.6
  }, {
    "id": 4,
    "page": 1,
    "sy": 5569.16,
    "y": 28077.8,
    "sx": 16099.1,
    "x": 2551.18
  }, {
    "id": 5,
    "page": 1,
    "sy": 5569.16,
    "y": 28077.8,
    "sx": 14525.3,
    "x": 18650.3
  }, {
    "id": 6,
    "page": 1,
    "sy": 5357.48,
    "y": 38111.5,
    "sx": 18016.2,
    "x": 2551.18
  }, {
    "id": 7,
    "page": 1,
    "sy": 5357.48,
    "y": 38111.5,
    "sx": 12608.2,
    "x": 20567.4
  }, {
    "id": 8,
    "page": 2,
    "sy": 5537.74,
    "y": 4634.65,
    "sx": 17180.1,
    "x": 2551.18
  }, {
    "id": 9,
    "page": 2,
    "sy": 5537.74,
    "y": 4634.65,
    "sx": 13444.3,
    "x": 19731.3
  }, {
    "id": 10,
    "page": 2,
    "sy": 5357.48,
    "y": 13412.6,
    "sx": 16580.6,
    "x": 2551.18
  }, {
    "id": 11,
    "page": 2,
    "sy": 5357.48,
    "y": 13412.6,
    "sx": 14043.8,
    "x": 19131.8
  }, {
    "id": 12,
    "page": 2,
    "sy": 6071.78,
    "y": 22010.3,
    "sx": 17334.1,
    "x": 2551.18
  }, {
    "id": 13,
    "page": 2,
    "sy": 6071.78,
    "y": 22010.3,
    "sx": 13290.3,
    "x": 19885.2
  }, {
    "id": 14,
    "page": 2,
    "sy": 5946.99,
    "y": 31322.3,
    "sx": 16570.8,
    "x": 2551.18
  }, {
    "id": 15,
    "page": 2,
    "sy": 5946.99,
    "y": 31322.3,
    "sx": 14053.6,
    "x": 19122
  }, {
    "id": 16,
    "page": 2,
    "sy": 5357.48,
    "y": 40509.5,
    "sx": 16991.7,
    "x": 2551.18
  }, {
    "id": 17,
    "page": 2,
    "sy": 5357.48,
    "y": 40509.5,
    "sx": 13632.7,
    "x": 19542.9
  }, {
    "id": 18,
    "page": 3,
    "sy": 5357.48,
    "y": 4634.65,
    "sx": 16382.3,
    "x": 2551.18
  }, {
    "id": 19,
    "page": 3,
    "sy": 5357.48,
    "y": 4634.65,
    "sx": 14242.1,
    "x": 18933.5
  }, {
    "id": 20,
    "page": 3,
    "sy": 5357.48,
    "y": 13264.4,
    "sx": 16594.4,
    "x": 2551.18
  }, {
    "id": 21,
    "page": 3,
    "sy": 5357.48,
    "y": 13264.4,
    "sx": 14030,
    "x": 19145.6
  }, {
    "id": 22,
    "page": 3,
    "sy": 6244.63,
    "y": 21894.1,
    "sx": 16127.6,
    "x": 2551.18
  }, {
    "id": 23,
    "page": 3,
    "sy": 6244.63,
    "y": 21894.1,
    "sx": 14496.8,
    "x": 18678.8
  }, {
    "id": 24,
    "page": 3,
    "sy": 5495.88,
    "y": 31411,
    "sx": 16547.5,
    "x": 2551.18
  }, {
    "id": 25,
    "page": 3,
    "sy": 5495.88,
    "y": 31411,
    "sx": 14076.9,
    "x": 19098.7
  }, {
    "id": 26,
    "page": 3,
    "sy": 5687.86,
    "y": 40179.2,
    "sx": 16949.9,
    "x": 2551.18
  }, {
    "id": 27,
    "page": 3,
    "sy": 5687.86,
    "y": 40179.2,
    "sx": 13674.5,
    "x": 19501.1
  }, {
    "id": 28,
    "page": 4,
    "sy": 5504.32,
    "y": 4634.65,
    "sx": 16134.3,
    "x": 2551.18
  }, {
    "id": 29,
    "page": 4,
    "sy": 5504.32,
    "y": 4634.65,
    "sx": 14490.1,
    "x": 18685.5
  }, {
    "id": 30,
    "page": 4,
    "sy": 5357.48,
    "y": 13524.5,
    "sx": 16466.6,
    "x": 2551.18
  }, {
    "id": 31,
    "page": 4,
    "sy": 5357.48,
    "y": 13524.5,
    "sx": 14157.8,
    "x": 19017.8
  }, {
    "id": 32,
    "page": 4,
    "sy": 5515.17,
    "y": 22267.5,
    "sx": 17072.8,
    "x": 2551.18
  }, {
    "id": 33,
    "page": 4,
    "sy": 5515.17,
    "y": 22267.5,
    "sx": 13551.6,
    "x": 19624
  }, {
    "id": 34,
    "page": 4,
    "sy": 5798.17,
    "y": 31168.2,
    "sx": 17860.9,
    "x": 2551.18
  }, {
    "id": 35,
    "page": 4,
    "sy": 5798.17,
    "y": 31168.2,
    "sx": 12763.5,
    "x": 20412
  }, {
    "id": 36,
    "page": 4,
    "sy": 5515.06,
    "y": 40352,
    "sx": 17062.3,
    "x": 2551.18
  }, {
    "id": 37,
    "page": 4,
    "sy": 5515.06,
    "y": 40352,
    "sx": 13562.1,
    "x": 19613.5
  }, {
    "id": 38,
    "page": 5,
    "sy": 5357.48,
    "y": 4634.65,
    "sx": 17065.3,
    "x": 2551.18
  }, {
    "id": 39,
    "page": 5,
    "sy": 5357.48,
    "y": 4634.65,
    "sx": 13559,
    "x": 19616.5
  }, {
    "id": 40,
    "page": 5,
    "sy": 5357.48,
    "y": 13534.2,
    "sx": 16619.2,
    "x": 2551.18
  }, {
    "id": 41,
    "page": 5,
    "sy": 5357.48,
    "y": 13534.2,
    "sx": 14005.2,
    "x": 19170.4
  }, {
    "id": 42,
    "page": 5,
    "sy": 5357.48,
    "y": 22433.7,
    "sx": 15843.2,
    "x": 2551.18
  }, {
    "id": 43,
    "page": 5,
    "sy": 5357.48,
    "y": 22433.7,
    "sx": 14781.1,
    "x": 18394.4
  }, {
    "id": 44,
    "page": 5,
    "sy": 5495.88,
    "y": 31333.2,
    "sx": 15906.2,
    "x": 2551.18
  }, {
    "id": 45,
    "page": 5,
    "sy": 5495.88,
    "y": 31333.2,
    "sx": 14718.2,
    "x": 18457.3
  }, {
    "id": 46,
    "page": 5,
    "sy": 5495.88,
    "y": 40371.1,
    "sx": 17328.9,
    "x": 2551.18
  }, {
    "id": 47,
    "page": 5,
    "sy": 5495.88,
    "y": 40371.1,
    "sx": 13295.5,
    "x": 19880.1
  }, {
    "id": 48,
    "page": 6,
    "sy": 6255.54,
    "y": 4725.08,
    "sx": 16426.4,
    "x": 2551.18
  }, {
    "id": 49,
    "page": 6,
    "sy": 6255.54,
    "y": 4725.08,
    "sx": 14197.9,
    "x": 18977.6
  }, {
    "id": 50,
    "page": 6,
    "sy": 5569.16,
    "y": 15445.2,
    "sx": 16433,
    "x": 2551.18
  }, {
    "id": 51,
    "page": 6,
    "sy": 5569.16,
    "y": 15445.2,
    "sx": 14191.4,
    "x": 18984.2
  }, {
    "id": 52,
    "page": 6,
    "sy": 5798.17,
    "y": 25478.9,
    "sx": 12397.5,
    "x": 2551.18
  }, {
    "id": 53,
    "page": 6,
    "sy": 5798.17,
    "y": 25478.9,
    "sx": 9517.39,
    "x": 14948.6
  }, {
    "id": 54,
    "page": 6,
    "sy": 5798.17,
    "y": 25478.9,
    "sx": 8709.53,
    "x": 24466
  }]
}
