{
"pages":3,
"measures":49,
"time": [{
    "position": 0,
    "elid": 0
  }, {
    "position": 2286,
    "elid": 1
  }, {
    "position": 4571,
    "elid": 2
  }, {
    "position": 6857,
    "elid": 3
  }, {
    "position": 9143,
    "elid": 4
  }, {
    "position": 11429,
    "elid": 5
  }, {
    "position": 13714,
    "elid": 6
  }, {
    "position": 16000,
    "elid": 7
  }, {
    "position": 18286,
    "elid": 8
  }, {
    "position": 20571,
    "elid": 9
  }, {
    "position": 22857,
    "elid": 10
  }, {
    "position": 25143,
    "elid": 11
  }, {
    "position": 27429,
    "elid": 12
  }, {
    "position": 29714,
    "elid": 13
  }, {
    "position": 32000,
    "elid": 14
  }, {
    "position": 34286,
    "elid": 15
  }, {
    "position": 36571,
    "elid": 16
  }, {
    "position": 38857,
    "elid": 17
  }, {
    "position": 41143,
    "elid": 18
  }, {
    "position": 43429,
    "elid": 19
  }, {
    "position": 45714,
    "elid": 20
  }, {
    "position": 48000,
    "elid": 21
  }, {
    "position": 50286,
    "elid": 22
  }, {
    "position": 52571,
    "elid": 23
  }, {
    "position": 54857,
    "elid": 24
  }, {
    "position": 57143,
    "elid": 25
  }, {
    "position": 59429,
    "elid": 26
  }, {
    "position": 61714,
    "elid": 27
  }, {
    "position": 64000,
    "elid": 28
  }, {
    "position": 66286,
    "elid": 29
  }, {
    "position": 68571,
    "elid": 30
  }, {
    "position": 70857,
    "elid": 31
  }, {
    "position": 73143,
    "elid": 32
  }, {
    "position": 75429,
    "elid": 33
  }, {
    "position": 77714,
    "elid": 34
  }, {
    "position": 80000,
    "elid": 35
  }, {
    "position": 82286,
    "elid": 36
  }, {
    "position": 84571,
    "elid": 37
  }, {
    "position": 86857,
    "elid": 38
  }, {
    "position": 89143,
    "elid": 39
  }, {
    "position": 91429,
    "elid": 40
  }, {
    "position": 93714,
    "elid": 41
  }, {
    "position": 96000,
    "elid": 42
  }, {
    "position": 98286,
    "elid": 43
  }, {
    "position": 100571,
    "elid": 44
  }, {
    "position": 102857,
    "elid": 45
  }, {
    "position": 105143,
    "elid": 46
  }, {
    "position": 107429,
    "elid": 47
  }, {
    "position": 109714,
    "elid": 48
  }],
"space": [{
    "id": 0,
    "page": 1,
    "sy": 5357.48,
    "y": 7611.02,
    "sx": 11558.1,
    "x": 4039.37
  }, {
    "id": 1,
    "page": 1,
    "sy": 5357.48,
    "y": 7611.02,
    "sx": 8801.04,
    "x": 15597.5
  }, {
    "id": 2,
    "page": 1,
    "sy": 5357.48,
    "y": 7611.02,
    "sx": 8777.04,
    "x": 24398.5
  }, {
    "id": 3,
    "page": 1,
    "sy": 5357.48,
    "y": 15546.3,
    "sx": 9110.08,
    "x": 2551.18
  }, {
    "id": 4,
    "page": 1,
    "sy": 5357.48,
    "y": 15546.3,
    "sx": 7144.39,
    "x": 11661.3
  }, {
    "id": 5,
    "page": 1,
    "sy": 5357.48,
    "y": 15546.3,
    "sx": 7076.98,
    "x": 18805.7
  }, {
    "id": 6,
    "page": 1,
    "sy": 5357.48,
    "y": 15546.3,
    "sx": 7292.94,
    "x": 25882.6
  }, {
    "id": 7,
    "page": 1,
    "sy": 5357.48,
    "y": 23481.5,
    "sx": 11681.4,
    "x": 2551.18
  }, {
    "id": 8,
    "page": 1,
    "sy": 5357.48,
    "y": 23481.5,
    "sx": 9465.27,
    "x": 14232.5
  }, {
    "id": 9,
    "page": 1,
    "sy": 5357.48,
    "y": 23481.5,
    "sx": 9477.76,
    "x": 23697.8
  }, {
    "id": 10,
    "page": 1,
    "sy": 5782.11,
    "y": 31416.8,
    "sx": 12130.2,
    "x": 2551.18
  }, {
    "id": 11,
    "page": 1,
    "sy": 5782.11,
    "y": 31416.8,
    "sx": 9339.22,
    "x": 14681.4
  }, {
    "id": 12,
    "page": 1,
    "sy": 5782.11,
    "y": 31416.8,
    "sx": 9155,
    "x": 24020.6
  }, {
    "id": 13,
    "page": 1,
    "sy": 6090.32,
    "y": 39776.7,
    "sx": 9726.48,
    "x": 2551.18
  }, {
    "id": 14,
    "page": 1,
    "sy": 6090.32,
    "y": 39776.7,
    "sx": 7570.82,
    "x": 12277.7
  }, {
    "id": 15,
    "page": 1,
    "sy": 6090.32,
    "y": 39776.7,
    "sx": 6859.27,
    "x": 19848.5
  }, {
    "id": 16,
    "page": 1,
    "sy": 6090.32,
    "y": 39776.7,
    "sx": 6467.82,
    "x": 26707.8
  }, {
    "id": 17,
    "page": 2,
    "sy": 5593.18,
    "y": 4948.87,
    "sx": 11256.3,
    "x": 2551.18
  }, {
    "id": 18,
    "page": 2,
    "sy": 5593.18,
    "y": 4948.87,
    "sx": 9552.1,
    "x": 13807.5
  }, {
    "id": 19,
    "page": 2,
    "sy": 5593.18,
    "y": 4948.87,
    "sx": 9815.97,
    "x": 23359.6
  }, {
    "id": 20,
    "page": 2,
    "sy": 5500.39,
    "y": 13728.4,
    "sx": 9187.83,
    "x": 2551.18
  }, {
    "id": 21,
    "page": 2,
    "sy": 5500.39,
    "y": 13728.4,
    "sx": 7153.52,
    "x": 11739
  }, {
    "id": 22,
    "page": 2,
    "sy": 5500.39,
    "y": 13728.4,
    "sx": 7129.52,
    "x": 18892.5
  }, {
    "id": 23,
    "page": 2,
    "sy": 5500.39,
    "y": 13728.4,
    "sx": 7153.52,
    "x": 26022.1
  }, {
    "id": 24,
    "page": 2,
    "sy": 5357.48,
    "y": 22415.2,
    "sx": 11323.6,
    "x": 2551.18
  }, {
    "id": 25,
    "page": 2,
    "sy": 5357.48,
    "y": 22415.2,
    "sx": 9666.82,
    "x": 13874.8
  }, {
    "id": 26,
    "page": 2,
    "sy": 5357.48,
    "y": 22415.2,
    "sx": 9633.93,
    "x": 23541.6
  }, {
    "id": 27,
    "page": 2,
    "sy": 5856.47,
    "y": 30959.1,
    "sx": 9303.86,
    "x": 2551.18
  }, {
    "id": 28,
    "page": 2,
    "sy": 5856.47,
    "y": 30959.1,
    "sx": 7341.9,
    "x": 11855
  }, {
    "id": 29,
    "page": 2,
    "sy": 5856.47,
    "y": 30959.1,
    "sx": 6621.12,
    "x": 19196.9
  }, {
    "id": 30,
    "page": 2,
    "sy": 5856.47,
    "y": 30959.1,
    "sx": 7357.52,
    "x": 25818.1
  }, {
    "id": 31,
    "page": 2,
    "sy": 5865.05,
    "y": 40002,
    "sx": 9137.04,
    "x": 2551.18
  }, {
    "id": 32,
    "page": 2,
    "sy": 5865.05,
    "y": 40002,
    "sx": 7154.79,
    "x": 11688.2
  }, {
    "id": 33,
    "page": 2,
    "sy": 5865.05,
    "y": 40002,
    "sx": 7177.77,
    "x": 18843
  }, {
    "id": 34,
    "page": 2,
    "sy": 5865.05,
    "y": 40002,
    "sx": 7154.79,
    "x": 26020.8
  }, {
    "id": 35,
    "page": 3,
    "sy": 6440.08,
    "y": 4634.65,
    "sx": 9463.81,
    "x": 2551.18
  }, {
    "id": 36,
    "page": 3,
    "sy": 6440.08,
    "y": 4634.65,
    "sx": 7188.77,
    "x": 12015
  }, {
    "id": 37,
    "page": 3,
    "sy": 6440.08,
    "y": 4634.65,
    "sx": 6836.16,
    "x": 19203.8
  }, {
    "id": 38,
    "page": 3,
    "sy": 6440.08,
    "y": 4634.65,
    "sx": 7135.65,
    "x": 26039.9
  }, {
    "id": 39,
    "page": 3,
    "sy": 6366.92,
    "y": 15539.3,
    "sx": 9049.57,
    "x": 2551.18
  }, {
    "id": 40,
    "page": 3,
    "sy": 6366.92,
    "y": 15539.3,
    "sx": 6541.33,
    "x": 11600.8
  }, {
    "id": 41,
    "page": 3,
    "sy": 6366.92,
    "y": 15539.3,
    "sx": 7618.38,
    "x": 18142.1
  }, {
    "id": 42,
    "page": 3,
    "sy": 6366.92,
    "y": 15539.3,
    "sx": 7415.11,
    "x": 25760.5
  }, {
    "id": 43,
    "page": 3,
    "sy": 5613.66,
    "y": 26370.8,
    "sx": 11276.6,
    "x": 2551.18
  }, {
    "id": 44,
    "page": 3,
    "sy": 5613.66,
    "y": 26370.8,
    "sx": 10182.1,
    "x": 13827.8
  }, {
    "id": 45,
    "page": 3,
    "sy": 5613.66,
    "y": 26370.8,
    "sx": 9165.73,
    "x": 24009.8
  }, {
    "id": 46,
    "page": 3,
    "sy": 5357.48,
    "y": 36449,
    "sx": 14482.7,
    "x": 2551.18
  }, {
    "id": 47,
    "page": 3,
    "sy": 5357.48,
    "y": 36449,
    "sx": 8332.12,
    "x": 17033.9
  }, {
    "id": 48,
    "page": 3,
    "sy": 5357.48,
    "y": 36449,
    "sx": 7809.54,
    "x": 25366
  }]
}
