{
"pages":2,
"measures":30,
"time": [{
    "position": 0,
    "elid": 0
  }, {
    "position": 1846,
    "elid": 1
  }, {
    "position": 3692,
    "elid": 2
  }, {
    "position": 5538,
    "elid": 3
  }, {
    "position": 7385,
    "elid": 4
  }, {
    "position": 9231,
    "elid": 5
  }, {
    "position": 11077,
    "elid": 6
  }, {
    "position": 12923,
    "elid": 7
  }, {
    "position": 14769,
    "elid": 8
  }, {
    "position": 16615,
    "elid": 9
  }, {
    "position": 18462,
    "elid": 10
  }, {
    "position": 20308,
    "elid": 11
  }, {
    "position": 22154,
    "elid": 12
  }, {
    "position": 24000,
    "elid": 13
  }, {
    "position": 25846,
    "elid": 14
  }, {
    "position": 27692,
    "elid": 15
  }, {
    "position": 29538,
    "elid": 16
  }, {
    "position": 31385,
    "elid": 17
  }, {
    "position": 33231,
    "elid": 18
  }, {
    "position": 35077,
    "elid": 19
  }, {
    "position": 36923,
    "elid": 20
  }, {
    "position": 38769,
    "elid": 21
  }, {
    "position": 40615,
    "elid": 22
  }, {
    "position": 42462,
    "elid": 23
  }, {
    "position": 44308,
    "elid": 24
  }, {
    "position": 46154,
    "elid": 25
  }, {
    "position": 48000,
    "elid": 26
  }, {
    "position": 49846,
    "elid": 27
  }, {
    "position": 51692,
    "elid": 28
  }, {
    "position": 53538,
    "elid": 29
  }, {
    "position": 55385,
    "elid": 0
  }, {
    "position": 57231,
    "elid": 1
  }, {
    "position": 59077,
    "elid": 2
  }, {
    "position": 60923,
    "elid": 3
  }, {
    "position": 62769,
    "elid": 4
  }, {
    "position": 64615,
    "elid": 5
  }, {
    "position": 66462,
    "elid": 6
  }, {
    "position": 68308,
    "elid": 7
  }],
"space": [{
    "id": 0,
    "page": 1,
    "sy": 1190.55,
    "y": 7611.02,
    "sx": 15348.3,
    "x": 4039.37
  }, {
    "id": 1,
    "page": 1,
    "sy": 1190.55,
    "y": 7611.02,
    "sx": 13787.9,
    "x": 19387.7
  }, {
    "id": 2,
    "page": 1,
    "sy": 1190.55,
    "y": 12064.2,
    "sx": 12257.5,
    "x": 2551.18
  }, {
    "id": 3,
    "page": 1,
    "sy": 1190.55,
    "y": 12064.2,
    "sx": 9550.95,
    "x": 14808.7
  }, {
    "id": 4,
    "page": 1,
    "sy": 1190.55,
    "y": 12064.2,
    "sx": 8815.91,
    "x": 24359.7
  }, {
    "id": 5,
    "page": 1,
    "sy": 1190.55,
    "y": 16654.5,
    "sx": 16250.7,
    "x": 2551.18
  }, {
    "id": 6,
    "page": 1,
    "sy": 1190.55,
    "y": 16654.5,
    "sx": 14373.7,
    "x": 18801.9
  }, {
    "id": 7,
    "page": 1,
    "sy": 1190.55,
    "y": 21107.7,
    "sx": 10955.3,
    "x": 2551.18
  }, {
    "id": 8,
    "page": 1,
    "sy": 1190.55,
    "y": 21107.7,
    "sx": 9338.16,
    "x": 13506.5
  }, {
    "id": 9,
    "page": 1,
    "sy": 1190.55,
    "y": 21107.7,
    "sx": 10331,
    "x": 22844.6
  }, {
    "id": 10,
    "page": 1,
    "sy": 1190.55,
    "y": 26218.9,
    "sx": 16970.6,
    "x": 2551.18
  }, {
    "id": 11,
    "page": 1,
    "sy": 1190.55,
    "y": 26218.9,
    "sx": 13653.8,
    "x": 19521.8
  }, {
    "id": 12,
    "page": 1,
    "sy": 1190.55,
    "y": 30672.1,
    "sx": 15849,
    "x": 2551.18
  }, {
    "id": 13,
    "page": 1,
    "sy": 1190.55,
    "y": 30672.1,
    "sx": 14775.4,
    "x": 18400.2
  }, {
    "id": 14,
    "page": 1,
    "sy": 1190.55,
    "y": 35125.3,
    "sx": 16683.8,
    "x": 2551.18
  }, {
    "id": 15,
    "page": 1,
    "sy": 1190.55,
    "y": 35125.3,
    "sx": 13940.6,
    "x": 19235
  }, {
    "id": 16,
    "page": 1,
    "sy": 1190.55,
    "y": 40223.2,
    "sx": 16423.6,
    "x": 2551.18
  }, {
    "id": 17,
    "page": 1,
    "sy": 1190.55,
    "y": 40223.2,
    "sx": 14200.8,
    "x": 18974.8
  }, {
    "id": 18,
    "page": 1,
    "sy": 1190.55,
    "y": 44676.5,
    "sx": 16765.1,
    "x": 2551.18
  }, {
    "id": 19,
    "page": 1,
    "sy": 1190.55,
    "y": 44676.5,
    "sx": 13859.3,
    "x": 19316.2
  }, {
    "id": 20,
    "page": 2,
    "sy": 1190.55,
    "y": 4770.69,
    "sx": 16067.3,
    "x": 2551.18
  }, {
    "id": 21,
    "page": 2,
    "sy": 1190.55,
    "y": 4770.69,
    "sx": 14557.1,
    "x": 18618.5
  }, {
    "id": 22,
    "page": 2,
    "sy": 1190.55,
    "y": 10425.8,
    "sx": 17613.3,
    "x": 2551.18
  }, {
    "id": 23,
    "page": 2,
    "sy": 1190.55,
    "y": 10425.8,
    "sx": 13011.1,
    "x": 20164.4
  }, {
    "id": 24,
    "page": 2,
    "sy": 1190.55,
    "y": 16080.9,
    "sx": 16663.1,
    "x": 2551.18
  }, {
    "id": 25,
    "page": 2,
    "sy": 1190.55,
    "y": 16080.9,
    "sx": 13961.3,
    "x": 19214.3
  }, {
    "id": 26,
    "page": 2,
    "sy": 1190.55,
    "y": 21736,
    "sx": 17830.1,
    "x": 2551.18
  }, {
    "id": 27,
    "page": 2,
    "sy": 1190.55,
    "y": 21736,
    "sx": 12794.3,
    "x": 20381.2
  }, {
    "id": 28,
    "page": 2,
    "sy": 1190.55,
    "y": 27391.2,
    "sx": 16468.6,
    "x": 2551.18
  }, {
    "id": 29,
    "page": 2,
    "sy": 1190.55,
    "y": 27391.2,
    "sx": 14155.8,
    "x": 19019.7
  }]
}
