{
"pages":2,
"measures":54,
"time": [{
    "position": 0,
    "elid": 0
  }, {
    "position": 500,
    "elid": 1
  }, {
    "position": 2000,
    "elid": 2
  }, {
    "position": 3500,
    "elid": 3
  }, {
    "position": 5000,
    "elid": 4
  }, {
    "position": 6500,
    "elid": 5
  }, {
    "position": 8000,
    "elid": 6
  }, {
    "position": 9500,
    "elid": 7
  }, {
    "position": 11000,
    "elid": 8
  }, {
    "position": 12000,
    "elid": 0
  }, {
    "position": 12500,
    "elid": 1
  }, {
    "position": 14000,
    "elid": 2
  }, {
    "position": 15500,
    "elid": 3
  }, {
    "position": 17000,
    "elid": 4
  }, {
    "position": 18500,
    "elid": 5
  }, {
    "position": 20000,
    "elid": 6
  }, {
    "position": 21500,
    "elid": 7
  }, {
    "position": 23000,
    "elid": 8
  }, {
    "position": 24000,
    "elid": 9
  }, {
    "position": 24500,
    "elid": 10
  }, {
    "position": 26000,
    "elid": 11
  }, {
    "position": 27500,
    "elid": 12
  }, {
    "position": 29000,
    "elid": 13
  }, {
    "position": 30500,
    "elid": 14
  }, {
    "position": 32000,
    "elid": 15
  }, {
    "position": 33500,
    "elid": 16
  }, {
    "position": 35000,
    "elid": 17
  }, {
    "position": 36500,
    "elid": 18
  }, {
    "position": 38000,
    "elid": 19
  }, {
    "position": 39500,
    "elid": 20
  }, {
    "position": 41000,
    "elid": 21
  }, {
    "position": 42500,
    "elid": 22
  }, {
    "position": 44000,
    "elid": 23
  }, {
    "position": 45500,
    "elid": 24
  }, {
    "position": 47000,
    "elid": 25
  }, {
    "position": 48000,
    "elid": 9
  }, {
    "position": 48500,
    "elid": 10
  }, {
    "position": 50000,
    "elid": 11
  }, {
    "position": 51500,
    "elid": 12
  }, {
    "position": 53000,
    "elid": 13
  }, {
    "position": 54500,
    "elid": 14
  }, {
    "position": 56000,
    "elid": 15
  }, {
    "position": 57500,
    "elid": 16
  }, {
    "position": 59000,
    "elid": 17
  }, {
    "position": 60500,
    "elid": 18
  }, {
    "position": 62000,
    "elid": 19
  }, {
    "position": 63500,
    "elid": 20
  }, {
    "position": 65000,
    "elid": 21
  }, {
    "position": 66500,
    "elid": 22
  }, {
    "position": 68000,
    "elid": 23
  }, {
    "position": 69500,
    "elid": 24
  }, {
    "position": 71000,
    "elid": 25
  }, {
    "position": 72000,
    "elid": 26
  }, {
    "position": 72500,
    "elid": 27
  }, {
    "position": 74000,
    "elid": 28
  }, {
    "position": 75500,
    "elid": 29
  }, {
    "position": 77000,
    "elid": 30
  }, {
    "position": 78500,
    "elid": 31
  }, {
    "position": 80000,
    "elid": 32
  }, {
    "position": 81500,
    "elid": 33
  }, {
    "position": 83000,
    "elid": 34
  }, {
    "position": 84000,
    "elid": 26
  }, {
    "position": 84500,
    "elid": 27
  }, {
    "position": 86000,
    "elid": 28
  }, {
    "position": 87500,
    "elid": 29
  }, {
    "position": 89000,
    "elid": 30
  }, {
    "position": 90500,
    "elid": 31
  }, {
    "position": 92000,
    "elid": 32
  }, {
    "position": 93500,
    "elid": 33
  }, {
    "position": 95000,
    "elid": 34
  }, {
    "position": 96000,
    "elid": 35
  }, {
    "position": 96500,
    "elid": 36
  }, {
    "position": 98000,
    "elid": 37
  }, {
    "position": 99500,
    "elid": 38
  }, {
    "position": 101000,
    "elid": 39
  }, {
    "position": 102500,
    "elid": 40
  }, {
    "position": 104000,
    "elid": 41
  }, {
    "position": 105500,
    "elid": 42
  }, {
    "position": 107000,
    "elid": 43
  }, {
    "position": 108500,
    "elid": 44
  }, {
    "position": 110000,
    "elid": 45
  }, {
    "position": 111500,
    "elid": 46
  }, {
    "position": 113000,
    "elid": 47
  }, {
    "position": 114500,
    "elid": 48
  }, {
    "position": 116000,
    "elid": 49
  }, {
    "position": 117500,
    "elid": 50
  }, {
    "position": 119000,
    "elid": 51
  }, {
    "position": 120500,
    "elid": 52
  }, {
    "position": 122000,
    "elid": 53
  }],
"space": [{
    "id": 0,
    "page": 1,
    "sy": 5357.48,
    "y": 7611.02,
    "sx": 4350.94,
    "x": 4039.37
  }, {
    "id": 1,
    "page": 1,
    "sy": 5357.48,
    "y": 7611.02,
    "sx": 6013.81,
    "x": 8390.31
  }, {
    "id": 2,
    "page": 1,
    "sy": 5357.48,
    "y": 7611.02,
    "sx": 6372.82,
    "x": 14404.1
  }, {
    "id": 3,
    "page": 1,
    "sy": 5357.48,
    "y": 7611.02,
    "sx": 6384.82,
    "x": 20776.9
  }, {
    "id": 4,
    "page": 1,
    "sy": 5357.48,
    "y": 7611.02,
    "sx": 6013.81,
    "x": 27161.8
  }, {
    "id": 5,
    "page": 1,
    "sy": 5357.48,
    "y": 15835.7,
    "sx": 7745.01,
    "x": 2551.18
  }, {
    "id": 6,
    "page": 1,
    "sy": 5357.48,
    "y": 15835.7,
    "sx": 5824.64,
    "x": 10296.2
  }, {
    "id": 7,
    "page": 1,
    "sy": 5357.48,
    "y": 15835.7,
    "sx": 5824.64,
    "x": 16120.8
  }, {
    "id": 8,
    "page": 1,
    "sy": 5357.48,
    "y": 15835.7,
    "sx": 3209.03,
    "x": 21945.5
  }, {
    "id": 9,
    "page": 1,
    "sy": 5357.48,
    "y": 15835.7,
    "sx": 2076.32,
    "x": 25154.5
  }, {
    "id": 10,
    "page": 1,
    "sy": 5357.48,
    "y": 15835.7,
    "sx": 5944.76,
    "x": 27230.8
  }, {
    "id": 11,
    "page": 1,
    "sy": 5357.48,
    "y": 24060.3,
    "sx": 7577.42,
    "x": 2551.18
  }, {
    "id": 12,
    "page": 1,
    "sy": 5357.48,
    "y": 24060.3,
    "sx": 5881.35,
    "x": 10128.6
  }, {
    "id": 13,
    "page": 1,
    "sy": 5357.48,
    "y": 24060.3,
    "sx": 5731.41,
    "x": 16009.9
  }, {
    "id": 14,
    "page": 1,
    "sy": 5357.48,
    "y": 24060.3,
    "sx": 5777.17,
    "x": 21741.4
  }, {
    "id": 15,
    "page": 1,
    "sy": 5357.48,
    "y": 24060.3,
    "sx": 5657.05,
    "x": 27518.5
  }, {
    "id": 16,
    "page": 1,
    "sy": 5357.48,
    "y": 32284.9,
    "sx": 8349.17,
    "x": 2551.18
  }, {
    "id": 17,
    "page": 1,
    "sy": 5357.48,
    "y": 32284.9,
    "sx": 5669.02,
    "x": 10900.4
  }, {
    "id": 18,
    "page": 1,
    "sy": 5357.48,
    "y": 32284.9,
    "sx": 5535.4,
    "x": 16569.4
  }, {
    "id": 19,
    "page": 1,
    "sy": 5357.48,
    "y": 32284.9,
    "sx": 5535.4,
    "x": 22104.8
  }, {
    "id": 20,
    "page": 1,
    "sy": 5357.48,
    "y": 32284.9,
    "sx": 5535.4,
    "x": 27640.2
  }, {
    "id": 21,
    "page": 1,
    "sy": 5357.48,
    "y": 40509.5,
    "sx": 7598.67,
    "x": 2551.18
  }, {
    "id": 22,
    "page": 1,
    "sy": 5357.48,
    "y": 40509.5,
    "sx": 5678.3,
    "x": 10149.9
  }, {
    "id": 23,
    "page": 1,
    "sy": 5357.48,
    "y": 40509.5,
    "sx": 5678.3,
    "x": 15828.2
  }, {
    "id": 24,
    "page": 1,
    "sy": 5357.48,
    "y": 40509.5,
    "sx": 5678.3,
    "x": 21506.5
  }, {
    "id": 25,
    "page": 1,
    "sy": 5357.48,
    "y": 40509.5,
    "sx": 3111.47,
    "x": 27184.8
  }, {
    "id": 26,
    "page": 1,
    "sy": 5357.48,
    "y": 40509.5,
    "sx": 2879.34,
    "x": 30296.2
  }, {
    "id": 27,
    "page": 2,
    "sy": 5357.48,
    "y": 4634.65,
    "sx": 7920.44,
    "x": 2551.18
  }, {
    "id": 28,
    "page": 2,
    "sy": 5357.48,
    "y": 4634.65,
    "sx": 5427.4,
    "x": 10471.6
  }, {
    "id": 29,
    "page": 2,
    "sy": 5357.48,
    "y": 4634.65,
    "sx": 6409.97,
    "x": 15899
  }, {
    "id": 30,
    "page": 2,
    "sy": 5357.48,
    "y": 4634.65,
    "sx": 5439.2,
    "x": 22309
  }, {
    "id": 31,
    "page": 2,
    "sy": 5357.48,
    "y": 4634.65,
    "sx": 5427.4,
    "x": 27748.2
  }, {
    "id": 32,
    "page": 2,
    "sy": 5357.48,
    "y": 13603.4,
    "sx": 7623.51,
    "x": 2551.18
  }, {
    "id": 33,
    "page": 2,
    "sy": 5357.48,
    "y": 13603.4,
    "sx": 6196.24,
    "x": 10174.7
  }, {
    "id": 34,
    "page": 2,
    "sy": 5357.48,
    "y": 13603.4,
    "sx": 2510.73,
    "x": 16370.9
  }, {
    "id": 35,
    "page": 2,
    "sy": 5357.48,
    "y": 13603.4,
    "sx": 2887.62,
    "x": 18881.7
  }, {
    "id": 36,
    "page": 2,
    "sy": 5357.48,
    "y": 13603.4,
    "sx": 5703.15,
    "x": 21769.3
  }, {
    "id": 37,
    "page": 2,
    "sy": 5357.48,
    "y": 13603.4,
    "sx": 5703.15,
    "x": 27472.4
  }, {
    "id": 38,
    "page": 2,
    "sy": 5357.48,
    "y": 22572.1,
    "sx": 7661.17,
    "x": 2551.18
  }, {
    "id": 39,
    "page": 2,
    "sy": 5357.48,
    "y": 22572.1,
    "sx": 5740.81,
    "x": 10212.4
  }, {
    "id": 40,
    "page": 2,
    "sy": 5357.48,
    "y": 22572.1,
    "sx": 5740.81,
    "x": 15953.2
  }, {
    "id": 41,
    "page": 2,
    "sy": 5357.48,
    "y": 22572.1,
    "sx": 5740.81,
    "x": 21694
  }, {
    "id": 42,
    "page": 2,
    "sy": 5357.48,
    "y": 22572.1,
    "sx": 5740.81,
    "x": 27434.8
  }, {
    "id": 43,
    "page": 2,
    "sy": 5357.48,
    "y": 31540.8,
    "sx": 7523.59,
    "x": 2551.18
  }, {
    "id": 44,
    "page": 2,
    "sy": 5357.48,
    "y": 31540.8,
    "sx": 5810.32,
    "x": 10074.8
  }, {
    "id": 45,
    "page": 2,
    "sy": 5357.48,
    "y": 31540.8,
    "sx": 6009.67,
    "x": 15885.1
  }, {
    "id": 46,
    "page": 2,
    "sy": 5357.48,
    "y": 31540.8,
    "sx": 5677.59,
    "x": 21894.8
  }, {
    "id": 47,
    "page": 2,
    "sy": 5357.48,
    "y": 31540.8,
    "sx": 5603.22,
    "x": 27572.4
  }, {
    "id": 48,
    "page": 2,
    "sy": 5357.48,
    "y": 40509.5,
    "sx": 7853.59,
    "x": 2551.18
  }, {
    "id": 49,
    "page": 2,
    "sy": 5357.48,
    "y": 40509.5,
    "sx": 5568.34,
    "x": 10404.8
  }, {
    "id": 50,
    "page": 2,
    "sy": 5357.48,
    "y": 40509.5,
    "sx": 5642.7,
    "x": 15973.1
  }, {
    "id": 51,
    "page": 2,
    "sy": 5357.48,
    "y": 40509.5,
    "sx": 2757.56,
    "x": 21615.8
  }, {
    "id": 52,
    "page": 2,
    "sy": 5357.48,
    "y": 40509.5,
    "sx": 5568.34,
    "x": 24373.4
  }, {
    "id": 53,
    "page": 2,
    "sy": 5357.48,
    "y": 40509.5,
    "sx": 3233.88,
    "x": 29941.7
  }]
}
