{
"pages":2,
"measures":51,
"time": [{
    "position": 0,
    "elid": 0
  }, {
    "position": 526,
    "elid": 1
  }, {
    "position": 1579,
    "elid": 2
  }, {
    "position": 2632,
    "elid": 3
  }, {
    "position": 3684,
    "elid": 4
  }, {
    "position": 4737,
    "elid": 5
  }, {
    "position": 5789,
    "elid": 6
  }, {
    "position": 6842,
    "elid": 7
  }, {
    "position": 7895,
    "elid": 8
  }, {
    "position": 8947,
    "elid": 9
  }, {
    "position": 10000,
    "elid": 10
  }, {
    "position": 11053,
    "elid": 11
  }, {
    "position": 12105,
    "elid": 12
  }, {
    "position": 13158,
    "elid": 13
  }, {
    "position": 14211,
    "elid": 14
  }, {
    "position": 15263,
    "elid": 15
  }, {
    "position": 16316,
    "elid": 16
  }, {
    "position": 17368,
    "elid": 17
  }, {
    "position": 18421,
    "elid": 18
  }, {
    "position": 19474,
    "elid": 19
  }, {
    "position": 20526,
    "elid": 20
  }, {
    "position": 21579,
    "elid": 21
  }, {
    "position": 22632,
    "elid": 22
  }, {
    "position": 23684,
    "elid": 23
  }, {
    "position": 24737,
    "elid": 24
  }, {
    "position": 25789,
    "elid": 25
  }, {
    "position": 26842,
    "elid": 26
  }, {
    "position": 27895,
    "elid": 27
  }, {
    "position": 28947,
    "elid": 28
  }, {
    "position": 30000,
    "elid": 29
  }, {
    "position": 31053,
    "elid": 30
  }, {
    "position": 32105,
    "elid": 31
  }, {
    "position": 33158,
    "elid": 32
  }, {
    "position": 34211,
    "elid": 33
  }, {
    "position": 35263,
    "elid": 34
  }, {
    "position": 36316,
    "elid": 35
  }, {
    "position": 37368,
    "elid": 36
  }, {
    "position": 38421,
    "elid": 37
  }, {
    "position": 39474,
    "elid": 38
  }, {
    "position": 40526,
    "elid": 39
  }, {
    "position": 41579,
    "elid": 40
  }, {
    "position": 42632,
    "elid": 41
  }, {
    "position": 43684,
    "elid": 42
  }, {
    "position": 44737,
    "elid": 43
  }, {
    "position": 45789,
    "elid": 44
  }, {
    "position": 46842,
    "elid": 45
  }, {
    "position": 47895,
    "elid": 46
  }, {
    "position": 48947,
    "elid": 47
  }, {
    "position": 50000,
    "elid": 48
  }, {
    "position": 51053,
    "elid": 49
  }, {
    "position": 52105,
    "elid": 50
  }],
"space": [{
    "id": 0,
    "page": 1,
    "sy": 5357.48,
    "y": 7611.02,
    "sx": 5381.85,
    "x": 4039.37
  }, {
    "id": 1,
    "page": 1,
    "sy": 5357.48,
    "y": 7611.02,
    "sx": 5826.77,
    "x": 9421.22
  }, {
    "id": 2,
    "page": 1,
    "sy": 5357.48,
    "y": 7611.02,
    "sx": 6100.97,
    "x": 15248
  }, {
    "id": 3,
    "page": 1,
    "sy": 5357.48,
    "y": 7611.02,
    "sx": 6432.93,
    "x": 21349
  }, {
    "id": 4,
    "page": 1,
    "sy": 5357.48,
    "y": 7611.02,
    "sx": 5393.68,
    "x": 27781.9
  }, {
    "id": 5,
    "page": 1,
    "sy": 5357.48,
    "y": 15801.1,
    "sx": 8675.46,
    "x": 2551.18
  }, {
    "id": 6,
    "page": 1,
    "sy": 5357.48,
    "y": 15801.1,
    "sx": 7494.41,
    "x": 11226.6
  }, {
    "id": 7,
    "page": 1,
    "sy": 5357.48,
    "y": 15801.1,
    "sx": 7143.54,
    "x": 18721
  }, {
    "id": 8,
    "page": 1,
    "sy": 5357.48,
    "y": 15801.1,
    "sx": 7310.99,
    "x": 25864.6
  }, {
    "id": 9,
    "page": 1,
    "sy": 5495.88,
    "y": 23991.1,
    "sx": 8263.7,
    "x": 2551.18
  }, {
    "id": 10,
    "page": 1,
    "sy": 5495.88,
    "y": 23991.1,
    "sx": 7224.59,
    "x": 10814.9
  }, {
    "id": 11,
    "page": 1,
    "sy": 5495.88,
    "y": 23991.1,
    "sx": 3347.79,
    "x": 18039.5
  }, {
    "id": 12,
    "page": 1,
    "sy": 5495.88,
    "y": 23991.1,
    "sx": 4811.13,
    "x": 21387.3
  }, {
    "id": 13,
    "page": 1,
    "sy": 5495.88,
    "y": 23991.1,
    "sx": 6977.19,
    "x": 26198.4
  }, {
    "id": 14,
    "page": 1,
    "sy": 5357.48,
    "y": 32319.5,
    "sx": 7536.48,
    "x": 2551.18
  }, {
    "id": 15,
    "page": 1,
    "sy": 5357.48,
    "y": 32319.5,
    "sx": 6457.55,
    "x": 10087.7
  }, {
    "id": 16,
    "page": 1,
    "sy": 5357.48,
    "y": 32319.5,
    "sx": 5418.29,
    "x": 16545.2
  }, {
    "id": 17,
    "page": 1,
    "sy": 5357.48,
    "y": 32319.5,
    "sx": 5440.85,
    "x": 21963.5
  }, {
    "id": 18,
    "page": 1,
    "sy": 5357.48,
    "y": 32319.5,
    "sx": 5771.22,
    "x": 27404.4
  }, {
    "id": 19,
    "page": 1,
    "sy": 5357.48,
    "y": 40509.5,
    "sx": 7355.67,
    "x": 2551.18
  }, {
    "id": 20,
    "page": 1,
    "sy": 5357.48,
    "y": 40509.5,
    "sx": 5540,
    "x": 9906.85
  }, {
    "id": 21,
    "page": 1,
    "sy": 5357.48,
    "y": 40509.5,
    "sx": 5602.4,
    "x": 15446.9
  }, {
    "id": 22,
    "page": 1,
    "sy": 5357.48,
    "y": 40509.5,
    "sx": 5887.66,
    "x": 21049.3
  }, {
    "id": 23,
    "page": 1,
    "sy": 5357.48,
    "y": 40509.5,
    "sx": 6238.66,
    "x": 26936.9
  }, {
    "id": 24,
    "page": 2,
    "sy": 5357.48,
    "y": 4634.65,
    "sx": 7021.87,
    "x": 2551.18
  }, {
    "id": 25,
    "page": 2,
    "sy": 5357.48,
    "y": 4634.65,
    "sx": 5673.37,
    "x": 9573.05
  }, {
    "id": 26,
    "page": 2,
    "sy": 5357.48,
    "y": 4634.65,
    "sx": 5958.63,
    "x": 15246.4
  }, {
    "id": 27,
    "page": 2,
    "sy": 5357.48,
    "y": 4634.65,
    "sx": 6309.63,
    "x": 21205.1
  }, {
    "id": 28,
    "page": 2,
    "sy": 5357.48,
    "y": 4634.65,
    "sx": 5660.89,
    "x": 27514.7
  }, {
    "id": 29,
    "page": 2,
    "sy": 5495.88,
    "y": 13568.8,
    "sx": 4401.26,
    "x": 2551.18
  }, {
    "id": 30,
    "page": 2,
    "sy": 5495.88,
    "y": 13568.8,
    "sx": 3727.64,
    "x": 6952.44
  }, {
    "id": 31,
    "page": 2,
    "sy": 5495.88,
    "y": 13568.8,
    "sx": 5773.62,
    "x": 10680.1
  }, {
    "id": 32,
    "page": 2,
    "sy": 5495.88,
    "y": 13568.8,
    "sx": 5699.07,
    "x": 16453.7
  }, {
    "id": 33,
    "page": 2,
    "sy": 5495.88,
    "y": 13568.8,
    "sx": 6031.03,
    "x": 22152.8
  }, {
    "id": 34,
    "page": 2,
    "sy": 5495.88,
    "y": 13568.8,
    "sx": 4991.78,
    "x": 28183.8
  }, {
    "id": 35,
    "page": 2,
    "sy": 5357.48,
    "y": 22641.3,
    "sx": 8585.15,
    "x": 2551.18
  }, {
    "id": 36,
    "page": 2,
    "sy": 5357.48,
    "y": 22641.3,
    "sx": 7416.58,
    "x": 11136.3
  }, {
    "id": 37,
    "page": 2,
    "sy": 5357.48,
    "y": 22641.3,
    "sx": 7389.5,
    "x": 18552.9
  }, {
    "id": 38,
    "page": 2,
    "sy": 5357.48,
    "y": 22641.3,
    "sx": 7233.16,
    "x": 25942.4
  }, {
    "id": 39,
    "page": 2,
    "sy": 5357.48,
    "y": 31575.4,
    "sx": 7934.93,
    "x": 2551.18
  }, {
    "id": 40,
    "page": 2,
    "sy": 5357.48,
    "y": 31575.4,
    "sx": 6147.15,
    "x": 10486.1
  }, {
    "id": 41,
    "page": 2,
    "sy": 5357.48,
    "y": 31575.4,
    "sx": 2249.52,
    "x": 16633.3
  }, {
    "id": 42,
    "page": 2,
    "sy": 5357.48,
    "y": 31575.4,
    "sx": 2110.78,
    "x": 18882.8
  }, {
    "id": 43,
    "page": 2,
    "sy": 5357.48,
    "y": 31575.4,
    "sx": 3123.34,
    "x": 20993.6
  }, {
    "id": 44,
    "page": 2,
    "sy": 5357.48,
    "y": 31575.4,
    "sx": 2623.04,
    "x": 24116.9
  }, {
    "id": 45,
    "page": 2,
    "sy": 5357.48,
    "y": 31575.4,
    "sx": 3002.52,
    "x": 26739.9
  }, {
    "id": 46,
    "page": 2,
    "sy": 5357.48,
    "y": 31575.4,
    "sx": 3433.12,
    "x": 29742.5
  }, {
    "id": 47,
    "page": 2,
    "sy": 5357.48,
    "y": 40509.5,
    "sx": 8695.45,
    "x": 2551.18
  }, {
    "id": 48,
    "page": 2,
    "sy": 5357.48,
    "y": 40509.5,
    "sx": 7953.93,
    "x": 11246.6
  }, {
    "id": 49,
    "page": 2,
    "sy": 5357.48,
    "y": 40509.5,
    "sx": 7262.56,
    "x": 19200.6
  }, {
    "id": 50,
    "page": 2,
    "sy": 5357.48,
    "y": 40509.5,
    "sx": 6712.46,
    "x": 26463.1
  }]
}
