{
"pages":2,
"measures":92,
"time": [{
    "position": 0,
    "elid": 0
  }, {
    "position": 800,
    "elid": 1
  }, {
    "position": 2400,
    "elid": 2
  }, {
    "position": 4000,
    "elid": 3
  }, {
    "position": 5600,
    "elid": 4
  }, {
    "position": 7200,
    "elid": 5
  }, {
    "position": 8800,
    "elid": 6
  }, {
    "position": 10400,
    "elid": 7
  }, {
    "position": 12000,
    "elid": 8
  }, {
    "position": 13600,
    "elid": 9
  }, {
    "position": 15200,
    "elid": 10
  }, {
    "position": 16800,
    "elid": 11
  }, {
    "position": 18400,
    "elid": 12
  }, {
    "position": 20000,
    "elid": 13
  }, {
    "position": 21600,
    "elid": 14
  }, {
    "position": 23200,
    "elid": 15
  }, {
    "position": 24800,
    "elid": 16
  }, {
    "position": 26400,
    "elid": 17
  }, {
    "position": 28000,
    "elid": 18
  }, {
    "position": 29600,
    "elid": 19
  }, {
    "position": 31200,
    "elid": 20
  }, {
    "position": 32800,
    "elid": 21
  }, {
    "position": 34400,
    "elid": 22
  }, {
    "position": 36000,
    "elid": 23
  }, {
    "position": 37600,
    "elid": 24
  }, {
    "position": 39200,
    "elid": 25
  }, {
    "position": 40800,
    "elid": 26
  }, {
    "position": 42400,
    "elid": 27
  }, {
    "position": 44000,
    "elid": 28
  }, {
    "position": 45600,
    "elid": 29
  }, {
    "position": 47200,
    "elid": 30
  }, {
    "position": 48800,
    "elid": 31
  }, {
    "position": 50400,
    "elid": 32
  }, {
    "position": 52000,
    "elid": 33
  }, {
    "position": 53600,
    "elid": 34
  }, {
    "position": 55200,
    "elid": 35
  }, {
    "position": 56800,
    "elid": 36
  }, {
    "position": 58400,
    "elid": 37
  }, {
    "position": 60000,
    "elid": 38
  }, {
    "position": 61600,
    "elid": 39
  }, {
    "position": 63200,
    "elid": 40
  }, {
    "position": 64800,
    "elid": 41
  }, {
    "position": 66400,
    "elid": 42
  }, {
    "position": 68000,
    "elid": 43
  }, {
    "position": 69600,
    "elid": 44
  }, {
    "position": 71200,
    "elid": 45
  }, {
    "position": 72800,
    "elid": 46
  }, {
    "position": 74400,
    "elid": 47
  }, {
    "position": 76000,
    "elid": 48
  }, {
    "position": 77600,
    "elid": 49
  }, {
    "position": 79200,
    "elid": 50
  }, {
    "position": 80800,
    "elid": 51
  }, {
    "position": 82400,
    "elid": 52
  }, {
    "position": 84000,
    "elid": 53
  }, {
    "position": 85600,
    "elid": 54
  }, {
    "position": 87200,
    "elid": 55
  }, {
    "position": 88800,
    "elid": 56
  }, {
    "position": 90400,
    "elid": 57
  }, {
    "position": 92000,
    "elid": 58
  }, {
    "position": 93600,
    "elid": 59
  }, {
    "position": 95200,
    "elid": 60
  }, {
    "position": 96800,
    "elid": 61
  }, {
    "position": 98400,
    "elid": 62
  }, {
    "position": 100000,
    "elid": 63
  }, {
    "position": 101600,
    "elid": 64
  }, {
    "position": 103200,
    "elid": 65
  }, {
    "position": 104800,
    "elid": 66
  }, {
    "position": 106400,
    "elid": 67
  }, {
    "position": 108000,
    "elid": 68
  }, {
    "position": 109600,
    "elid": 69
  }, {
    "position": 111200,
    "elid": 70
  }, {
    "position": 112800,
    "elid": 71
  }, {
    "position": 114400,
    "elid": 72
  }, {
    "position": 116000,
    "elid": 73
  }, {
    "position": 117600,
    "elid": 74
  }, {
    "position": 119200,
    "elid": 75
  }, {
    "position": 120800,
    "elid": 76
  }, {
    "position": 122400,
    "elid": 77
  }, {
    "position": 124000,
    "elid": 78
  }, {
    "position": 125600,
    "elid": 79
  }, {
    "position": 127200,
    "elid": 80
  }, {
    "position": 128800,
    "elid": 81
  }, {
    "position": 130400,
    "elid": 82
  }, {
    "position": 132000,
    "elid": 83
  }, {
    "position": 133600,
    "elid": 84
  }, {
    "position": 135200,
    "elid": 85
  }, {
    "position": 136800,
    "elid": 86
  }, {
    "position": 138400,
    "elid": 87
  }, {
    "position": 140000,
    "elid": 88
  }, {
    "position": 141600,
    "elid": 89
  }, {
    "position": 143200,
    "elid": 90
  }, {
    "position": 144800,
    "elid": 91
  }],
"space": [{
    "id": 0,
    "page": 1,
    "sy": 1190.55,
    "y": 7611.02,
    "sx": 5596.08,
    "x": 4039.37
  }, {
    "id": 1,
    "page": 1,
    "sy": 1190.55,
    "y": 7611.02,
    "sx": 6027.34,
    "x": 9635.45
  }, {
    "id": 2,
    "page": 1,
    "sy": 1190.55,
    "y": 7611.02,
    "sx": 6319.51,
    "x": 15662.8
  }, {
    "id": 3,
    "page": 1,
    "sy": 1190.55,
    "y": 7611.02,
    "sx": 5833.34,
    "x": 21982.3
  }, {
    "id": 4,
    "page": 1,
    "sy": 1190.55,
    "y": 7611.02,
    "sx": 5359.93,
    "x": 27815.6
  }, {
    "id": 5,
    "page": 1,
    "sy": 1190.55,
    "y": 12205.3,
    "sx": 8537.48,
    "x": 2551.18
  }, {
    "id": 6,
    "page": 1,
    "sy": 1190.55,
    "y": 12205.3,
    "sx": 5685.04,
    "x": 11088.7
  }, {
    "id": 7,
    "page": 1,
    "sy": 1190.55,
    "y": 12205.3,
    "sx": 5237.1,
    "x": 16773.7
  }, {
    "id": 8,
    "page": 1,
    "sy": 1190.55,
    "y": 12205.3,
    "sx": 5176.71,
    "x": 22010.8
  }, {
    "id": 9,
    "page": 1,
    "sy": 1190.55,
    "y": 12205.3,
    "sx": 5988.06,
    "x": 27187.5
  }, {
    "id": 10,
    "page": 1,
    "sy": 1190.55,
    "y": 16799.6,
    "sx": 8134.85,
    "x": 2551.18
  }, {
    "id": 11,
    "page": 1,
    "sy": 1190.55,
    "y": 16799.6,
    "sx": 6189.41,
    "x": 10686
  }, {
    "id": 12,
    "page": 1,
    "sy": 1190.55,
    "y": 16799.6,
    "sx": 4972.28,
    "x": 16875.4
  }, {
    "id": 13,
    "page": 1,
    "sy": 1190.55,
    "y": 16799.6,
    "sx": 5716.01,
    "x": 21847.7
  }, {
    "id": 14,
    "page": 1,
    "sy": 1190.55,
    "y": 16799.6,
    "sx": 5611.84,
    "x": 27563.7
  }, {
    "id": 15,
    "page": 1,
    "sy": 1190.55,
    "y": 21393.9,
    "sx": 8114.59,
    "x": 2551.18
  }, {
    "id": 16,
    "page": 1,
    "sy": 1190.55,
    "y": 21393.9,
    "sx": 5710.79,
    "x": 10665.8
  }, {
    "id": 17,
    "page": 1,
    "sy": 1190.55,
    "y": 21393.9,
    "sx": 5367.02,
    "x": 16376.6
  }, {
    "id": 18,
    "page": 1,
    "sy": 1190.55,
    "y": 21393.9,
    "sx": 5262.85,
    "x": 21743.6
  }, {
    "id": 19,
    "page": 1,
    "sy": 1190.55,
    "y": 21393.9,
    "sx": 6169.15,
    "x": 27006.4
  }, {
    "id": 20,
    "page": 1,
    "sy": 1190.55,
    "y": 25988.2,
    "sx": 8276.12,
    "x": 2551.18
  }, {
    "id": 21,
    "page": 1,
    "sy": 1190.55,
    "y": 25988.2,
    "sx": 5857.29,
    "x": 10827.3
  }, {
    "id": 22,
    "page": 1,
    "sy": 1190.55,
    "y": 25988.2,
    "sx": 5408.64,
    "x": 16684.6
  }, {
    "id": 23,
    "page": 1,
    "sy": 1190.55,
    "y": 25988.2,
    "sx": 5777.87,
    "x": 22093.2
  }, {
    "id": 24,
    "page": 1,
    "sy": 1190.55,
    "y": 25988.2,
    "sx": 5304.47,
    "x": 27871.1
  }, {
    "id": 25,
    "page": 1,
    "sy": 1190.55,
    "y": 30582.5,
    "sx": 8840.23,
    "x": 2551.18
  }, {
    "id": 26,
    "page": 1,
    "sy": 1190.55,
    "y": 30582.5,
    "sx": 5987.79,
    "x": 11391.4
  }, {
    "id": 27,
    "page": 1,
    "sy": 1190.55,
    "y": 30582.5,
    "sx": 5539.85,
    "x": 17379.2
  }, {
    "id": 28,
    "page": 1,
    "sy": 1190.55,
    "y": 30582.5,
    "sx": 4637.26,
    "x": 22919.1
  }, {
    "id": 29,
    "page": 1,
    "sy": 1190.55,
    "y": 30582.5,
    "sx": 5619.26,
    "x": 27556.3
  }, {
    "id": 30,
    "page": 1,
    "sy": 1190.55,
    "y": 35410,
    "sx": 7913.16,
    "x": 2551.18
  }, {
    "id": 31,
    "page": 1,
    "sy": 1190.55,
    "y": 35410,
    "sx": 6445.39,
    "x": 10464.3
  }, {
    "id": 32,
    "page": 1,
    "sy": 1190.55,
    "y": 35410,
    "sx": 5065.02,
    "x": 16909.7
  }, {
    "id": 33,
    "page": 1,
    "sy": 1190.55,
    "y": 35410,
    "sx": 5485.82,
    "x": 21974.8
  }, {
    "id": 34,
    "page": 1,
    "sy": 1190.55,
    "y": 35410,
    "sx": 5715,
    "x": 27460.6
  }, {
    "id": 35,
    "page": 1,
    "sy": 1190.55,
    "y": 40082.2,
    "sx": 8301.89,
    "x": 2551.18
  }, {
    "id": 36,
    "page": 1,
    "sy": 1190.55,
    "y": 40082.2,
    "sx": 4903.51,
    "x": 10853.1
  }, {
    "id": 37,
    "page": 1,
    "sy": 1190.55,
    "y": 40082.2,
    "sx": 5613.81,
    "x": 15756.6
  }, {
    "id": 38,
    "page": 1,
    "sy": 1190.55,
    "y": 40082.2,
    "sx": 5613.81,
    "x": 21370.4
  }, {
    "id": 39,
    "page": 1,
    "sy": 1190.55,
    "y": 40082.2,
    "sx": 6191.38,
    "x": 26984.2
  }, {
    "id": 40,
    "page": 1,
    "sy": 1190.55,
    "y": 44676.5,
    "sx": 8083.45,
    "x": 2551.18
  }, {
    "id": 41,
    "page": 1,
    "sy": 1190.55,
    "y": 44676.5,
    "sx": 7703.55,
    "x": 10634.6
  }, {
    "id": 42,
    "page": 1,
    "sy": 1190.55,
    "y": 44676.5,
    "sx": 7445.19,
    "x": 18338.2
  }, {
    "id": 43,
    "page": 1,
    "sy": 1190.55,
    "y": 44676.5,
    "sx": 7392.21,
    "x": 25783.4
  }, {
    "id": 44,
    "page": 2,
    "sy": 1190.55,
    "y": 4634.65,
    "sx": 8435.74,
    "x": 2551.18
  }, {
    "id": 45,
    "page": 2,
    "sy": 1190.55,
    "y": 4634.65,
    "sx": 5590.53,
    "x": 10986.9
  }, {
    "id": 46,
    "page": 2,
    "sy": 1190.55,
    "y": 4634.65,
    "sx": 6178.52,
    "x": 16577.5
  }, {
    "id": 47,
    "page": 2,
    "sy": 1190.55,
    "y": 4634.65,
    "sx": 5590.53,
    "x": 22756
  }, {
    "id": 48,
    "page": 2,
    "sy": 1190.55,
    "y": 4634.65,
    "sx": 4829.06,
    "x": 28346.5
  }, {
    "id": 49,
    "page": 2,
    "sy": 1190.55,
    "y": 8962.12,
    "sx": 7202.74,
    "x": 2551.18
  }, {
    "id": 50,
    "page": 2,
    "sy": 1190.55,
    "y": 8962.12,
    "sx": 5486.49,
    "x": 9753.92
  }, {
    "id": 51,
    "page": 2,
    "sy": 1190.55,
    "y": 8962.12,
    "sx": 6710.25,
    "x": 15240.4
  }, {
    "id": 52,
    "page": 2,
    "sy": 1190.55,
    "y": 8962.12,
    "sx": 5257.31,
    "x": 21950.7
  }, {
    "id": 53,
    "page": 2,
    "sy": 1190.55,
    "y": 8962.12,
    "sx": 5967.61,
    "x": 27208
  }, {
    "id": 54,
    "page": 2,
    "sy": 1190.55,
    "y": 13632,
    "sx": 9193.95,
    "x": 2551.18
  }, {
    "id": 55,
    "page": 2,
    "sy": 1190.55,
    "y": 13632,
    "sx": 5439.5,
    "x": 11745.1
  }, {
    "id": 56,
    "page": 2,
    "sy": 1190.55,
    "y": 13632,
    "sx": 5564.51,
    "x": 17184.6
  }, {
    "id": 57,
    "page": 2,
    "sy": 1190.55,
    "y": 13632,
    "sx": 5564.51,
    "x": 22749.1
  }, {
    "id": 58,
    "page": 2,
    "sy": 1190.55,
    "y": 13632,
    "sx": 4861.93,
    "x": 28313.6
  }, {
    "id": 59,
    "page": 2,
    "sy": 1190.55,
    "y": 17959.4,
    "sx": 7793.09,
    "x": 2551.18
  }, {
    "id": 60,
    "page": 2,
    "sy": 1190.55,
    "y": 17959.4,
    "sx": 5733.06,
    "x": 10344.3
  }, {
    "id": 61,
    "page": 2,
    "sy": 1190.55,
    "y": 17959.4,
    "sx": 5951.83,
    "x": 16077.3
  }, {
    "id": 62,
    "page": 2,
    "sy": 1190.55,
    "y": 17959.4,
    "sx": 5388.59,
    "x": 22029.2
  }, {
    "id": 63,
    "page": 2,
    "sy": 1190.55,
    "y": 17959.4,
    "sx": 5757.82,
    "x": 27417.8
  }, {
    "id": 64,
    "page": 2,
    "sy": 1190.55,
    "y": 22366.1,
    "sx": 7520.97,
    "x": 2551.18
  }, {
    "id": 65,
    "page": 2,
    "sy": 1190.55,
    "y": 22366.1,
    "sx": 6905.73,
    "x": 10072.2
  }, {
    "id": 66,
    "page": 2,
    "sy": 1190.55,
    "y": 22366.1,
    "sx": 5998.72,
    "x": 16977.9
  }, {
    "id": 67,
    "page": 2,
    "sy": 1190.55,
    "y": 22366.1,
    "sx": 5550.78,
    "x": 22976.6
  }, {
    "id": 68,
    "page": 2,
    "sy": 1190.55,
    "y": 22366.1,
    "sx": 4648.19,
    "x": 28527.4
  }, {
    "id": 69,
    "page": 2,
    "sy": 1190.55,
    "y": 27193.6,
    "sx": 7640.61,
    "x": 2551.18
  }, {
    "id": 70,
    "page": 2,
    "sy": 1190.55,
    "y": 27193.6,
    "sx": 6168.58,
    "x": 10191.8
  }, {
    "id": 71,
    "page": 2,
    "sy": 1190.55,
    "y": 27193.6,
    "sx": 6168.58,
    "x": 16360.4
  }, {
    "id": 72,
    "page": 2,
    "sy": 1190.55,
    "y": 27193.6,
    "sx": 4951.45,
    "x": 22529
  }, {
    "id": 73,
    "page": 2,
    "sy": 1190.55,
    "y": 27193.6,
    "sx": 5695.18,
    "x": 27480.4
  }, {
    "id": 74,
    "page": 2,
    "sy": 1190.55,
    "y": 31694.1,
    "sx": 8389.08,
    "x": 2551.18
  }, {
    "id": 75,
    "page": 2,
    "sy": 1190.55,
    "y": 31694.1,
    "sx": 7437.46,
    "x": 10940.3
  }, {
    "id": 76,
    "page": 2,
    "sy": 1190.55,
    "y": 31694.1,
    "sx": 7597.91,
    "x": 18377.7
  }, {
    "id": 77,
    "page": 2,
    "sy": 1190.55,
    "y": 31694.1,
    "sx": 7199.95,
    "x": 25975.6
  }, {
    "id": 78,
    "page": 2,
    "sy": 1190.55,
    "y": 36021.5,
    "sx": 8419.48,
    "x": 2551.18
  }, {
    "id": 79,
    "page": 2,
    "sy": 1190.55,
    "y": 36021.5,
    "sx": 7249.01,
    "x": 10970.7
  }, {
    "id": 80,
    "page": 2,
    "sy": 1190.55,
    "y": 36021.5,
    "sx": 6698.14,
    "x": 18219.7
  }, {
    "id": 81,
    "page": 2,
    "sy": 1190.55,
    "y": 36021.5,
    "sx": 8257.76,
    "x": 24917.8
  }, {
    "id": 82,
    "page": 2,
    "sy": 1190.55,
    "y": 40349,
    "sx": 8180,
    "x": 2551.18
  }, {
    "id": 83,
    "page": 2,
    "sy": 1190.55,
    "y": 40349,
    "sx": 5730.36,
    "x": 10731.2
  }, {
    "id": 84,
    "page": 2,
    "sy": 1190.55,
    "y": 40349,
    "sx": 4663.03,
    "x": 16461.5
  }, {
    "id": 85,
    "page": 2,
    "sy": 1190.55,
    "y": 40349,
    "sx": 5805.72,
    "x": 21124.6
  }, {
    "id": 86,
    "page": 2,
    "sy": 1190.55,
    "y": 40349,
    "sx": 6245.28,
    "x": 26930.3
  }, {
    "id": 87,
    "page": 2,
    "sy": 1190.55,
    "y": 44676.5,
    "sx": 9578.55,
    "x": 2551.18
  }, {
    "id": 88,
    "page": 2,
    "sy": 1190.55,
    "y": 44676.5,
    "sx": 6768.63,
    "x": 12129.7
  }, {
    "id": 89,
    "page": 2,
    "sy": 1190.55,
    "y": 44676.5,
    "sx": 6768.63,
    "x": 18898.4
  }, {
    "id": 90,
    "page": 2,
    "sy": 1190.55,
    "y": 44676.5,
    "sx": 3622.59,
    "x": 25667
  }, {
    "id": 91,
    "page": 2,
    "sy": 1190.55,
    "y": 44676.5,
    "sx": 3886,
    "x": 29289.6
  }]
}
